inventorize/__init__.py
inventorize-1.2.3.dist-info/LICENSE
inventorize-1.2.3.dist-info/METADATA
inventorize-1.2.3.dist-info/WHEEL
inventorize-1.2.3.dist-info/top_level.txt
inventorize-1.2.3.dist-info/RECORD
