Metadata-Version: 2.1
Name: inventorize
Version: 1.2.3
Summary: inventory analytics,revenue management and cost calculations for SKUs
Author: Haytham Omar
Author-email: haytham@rescaleanalytics.com
Keywords: inventory,pricing,markdowns
Classifier: Programming Language :: Python :: 3
Classifier: License :: OSI Approved :: MIT License
Classifier: Operating System :: OS Independent
Requires-Python: >=3.6
License-File: LICENSE
Requires-Dist: scipy
Requires-Dist: scikit-learn
Requires-Dist: pandas >=0.23.3
Requires-Dist: numpy >=1.14.5
Requires-Dist: plotly
Requires-Dist: statsmodels
